speedtest/__init__.py
speedtest/speed_test.py
speedtestrouter-0.0.2.dist-info/LICENSE.txt
speedtestrouter-0.0.2.dist-info/METADATA
speedtestrouter-0.0.2.dist-info/WHEEL
speedtestrouter-0.0.2.dist-info/top_level.txt
speedtestrouter-0.0.2.dist-info/RECORD
