Metadata-Version: 2.1
Name: speedtestrouter
Version: 0.0.2
Summary: SpeeTest For Routers
Home-page: UNKNOWN
Author: Trinetra S
Author-email: trinetra.s@vcti.io
License: UNKNOWN
Keywords: python,speedtest
Platform: UNKNOWN
Classifier: Development Status :: 1 - Planning
Classifier: Intended Audience :: Developers
Classifier: Programming Language :: Python :: 3
Classifier: Operating System :: Unix
Classifier: Operating System :: MacOS :: MacOS X
Classifier: Operating System :: Microsoft :: Windows
Requires-Dist: speedtest-cli
Requires-Dist: schedule
Requires-Dist: argparse
Requires-Dist: tqdm
